setup.py
choptools/__init__.py
choptools/pdb2zmat.py
choptools.egg-info/PKG-INFO
choptools.egg-info/SOURCES.txt
choptools.egg-info/dependency_links.txt
choptools.egg-info/entry_points.txt
choptools.egg-info/requires.txt
choptools.egg-info/top_level.txt