Metadata-Version: 1.1
Name: choptools
Version: 0.1
Summary: Python script to chop proteins and prepare z-matrices needed for MCPRO simulations.
Home-page: https://github.com/mc-robinson/choptools
Author: Matthew C. Robinson, Israel Cabeza de Vaca Lopez
Author-email: matthew.robinson@yale.edu
License: MIT
Keywords: computational chemistry,force fields,molecular dynamics
Platform: UNKNOWN
Classifier: Programming Language :: Python :: 3.6
Classifier: Topic :: Scientific/Engineering
